{
    "Type":  "CONTACT_FLOW",
    "Description":  "test basic schema with errors",
    "Name":  "zz-basic-test-errors-1980404794",
    "Content":  "{\"StartAction\":\"1a5a8f69-74f8-48df-b6e1-9e3fbd83c0a6\",\"Actions\":[{\"Transitions\":{\"NextAction\":\"ab27176a-8c74-4d60-90e7-ac333f521ee2\",\"Errors\":[],\"Conditions\":[]},\"Type\":\"MessageParticipant\",\"Identifier\":\"1a5a8f69-74f8-48df-b6e1-9e3fbd83c0a6\",\"Parameters\":{\"Text\":\"Hello from test flow.\"}},{\"Transitions\":{\"NextAction\":\"3a430395-3804-441e-a6d8-8427d33eba12\",\"Errors\":[{\"ErrorType\":\"NoMatchingError\",\"NextAction\":\"3a430395-3804-441e-a6d8-8427d33eba12\"},{\"ErrorType\":\"NoMatchingCondition\",\"NextAction\":\"3a430395-3804-441e-a6d8-8427d33eba12\"},{\"ErrorType\":\"InputTimeLimitExceeded\",\"NextAction\":\"3a430395-3804-441e-a6d8-8427d33eba12\"}],\"Conditions\":[]},\"Type\":\"GetParticipantInput\",\"Identifier\":\"ab27176a-8c74-4d60-90e7-ac333f521ee2\",\"Parameters\":{\"InputTimeLimitSeconds\":\"5\",\"StoreInput\":\"False\",\"Text\":\"Press 1.\"}},{\"Transitions\":{},\"Type\":\"DisconnectParticipant\",\"Identifier\":\"3a430395-3804-441e-a6d8-8427d33eba12\",\"Parameters\":{}}],\"Version\":\"2019-10-30\",\"Metadata\":{\"entryPointPosition\":{\"y\":40,\"x\":40},\"ActionMetadata\":{\"3a430395-3804-441e-a6d8-8427d33eba12\":{\"position\":{\"y\":40,\"x\":640}},\"ab27176a-8c74-4d60-90e7-ac333f521ee2\":{\"position\":{\"y\":40,\"x\":400}},\"1a5a8f69-74f8-48df-b6e1-9e3fbd83c0a6\":{\"position\":{\"y\":40,\"x\":160}}}}}",
    "InstanceId":  "0626aa86-d377-44c8-9311-84e4f230cc72"
}